BattleBreakers/__init__.py
BattleBreakers/auth.py
BattleBreakers/client.py
BattleBreakers/http.py
BattleBreakers-0.0.1.dist-info/METADATA
BattleBreakers-0.0.1.dist-info/WHEEL
BattleBreakers-0.0.1.dist-info/top_level.txt
BattleBreakers-0.0.1.dist-info/RECORD
