Metadata-Version: 2.1
Name: BattleBreakers
Version: 0.0.1
Summary: Async library for interacting with Battle Breakers/Epic Games API.
Home-page: https://github.com/xMistt/BattleBreakers
Author: xMistt
License: UNKNOWN
Platform: UNKNOWN
Classifier: Programming Language :: Python :: 3
Classifier: Operating System :: OS Independent
Requires-Python: >=3.6
Requires-Dist: aiohttp
Requires-Dist: asyncio
Requires-Dist: pyglet
